<?xml version="1.0" encoding="utf-8"?>
<ArrayOfEngineer xmlns:xsi="http://www.w3.org/2001/XMLSchema-instance" xmlns:xsd="http://www.w3.org/2001/XMLSchema">
  <Engineer>
    <Id>399677105</Id>
    <Name>Alice</Name>
    <Email>Alice@gmail.com</Email>
    <Level>AdvancedBeginner</Level>
  </Engineer>
  <Engineer>
    <Id>304347072</Id>
    <Name>Bob</Name>
    <Email>Bob@gmail.com</Email>
    <Level>Proficient</Level>
  </Engineer>
  <Engineer>
    <Id>230585347</Id>
    <Name>Carol</Name>
    <Email>Carol@gmail.com</Email>
    <Level>Competent</Level>
  </Engineer>
  <Engineer>
    <Id>379071732</Id>
    <Name>David</Name>
    <Email>David@gmail.com</Email>
    <Level>AdvancedBeginner</Level>
  </Engineer>
  <Engineer>
    <Id>222076476</Id>
    <Name>Emma</Name>
    <Email>Emma@gmail.com</Email>
    <Level>Competent</Level>
  </Engineer>
  <Engineer>
    <Id>220120968</Id>
    <Name>Frank</Name>
    <Email>Frank@gmail.com</Email>
    <Level>Novice</Level>
  </Engineer>
  <Engineer>
    <Id>289505375</Id>
    <Name>Grace</Name>
    <Email>Grace@gmail.com</Email>
    <Level>Proficient</Level>
  </Engineer>
  <Engineer>
    <Id>381982115</Id>
    <Name>Henry</Name>
    <Email>Henry@gmail.com</Email>
    <Level>Competent</Level>
  </Engineer>
  <Engineer>
    <Id>330828199</Id>
    <Name>Irene</Name>
    <Email>Irene@gmail.com</Email>
    <Level>Competent</Level>
  </Engineer>
  <Engineer>
    <Id>245821406</Id>
    <Name>Jack</Name>
    <Email>Jack@gmail.com</Email>
    <Level>Competent</Level>
  </Engineer>
  <Engineer>
    <Id>350156332</Id>
    <Name>Karen</Name>
    <Email>Karen@gmail.com</Email>
    <Level>Expert</Level>
  </Engineer>
  <Engineer>
    <Id>214599907</Id>
    <Name>Liam</Name>
    <Email>Liam@gmail.com</Email>
    <Level>Novice</Level>
  </Engineer>
  <Engineer>
    <Id>328276029</Id>
    <Name>Megan</Name>
    <Email>Megan@gmail.com</Email>
    <Level>Competent</Level>
  </Engineer>
  <Engineer>
    <Id>262083809</Id>
    <Name>Noah</Name>
    <Email>Noah@gmail.com</Email>
    <Level>Novice</Level>
  </Engineer>
  <Engineer>
    <Id>350666821</Id>
    <Name>Olivia</Name>
    <Email>Olivia@gmail.com</Email>
    <Level>Proficient</Level>
  </Engineer>
  <Engineer>
    <Id>384508508</Id>
    <Name>Peter</Name>
    <Email>Peter@gmail.com</Email>
    <Level>Competent</Level>
  </Engineer>
  <Engineer>
    <Id>257060662</Id>
    <Name>Quin</Name>
    <Email>Quin@gmail.com</Email>
    <Level>Proficient</Level>
  </Engineer>
  <Engineer>
    <Id>295511645</Id>
    <Name>Rachel</Name>
    <Email>Rachel@gmail.com</Email>
    <Level>Competent</Level>
  </Engineer>
  <Engineer>
    <Id>265469099</Id>
    <Name>Sam</Name>
    <Email>Sam@gmail.com</Email>
    <Level>Proficient</Level>
  </Engineer>
  <Engineer>
    <Id>226097478</Id>
    <Name>Taylor</Name>
    <Email>Taylor@gmail.com</Email>
    <Level>Expert</Level>
  </Engineer>
  <Engineer>
    <Id>224657014</Id>
    <Name>Ulysses</Name>
    <Email>Ulysses@gmail.com</Email>
    <Level>Novice</Level>
  </Engineer>
  <Engineer>
    <Id>276160564</Id>
    <Name>Victoria</Name>
    <Email>Victoria@gmail.com</Email>
    <Level>Proficient</Level>
  </Engineer>
  <Engineer>
    <Id>260327470</Id>
    <Name>William</Name>
    <Email>William@gmail.com</Email>
    <Level>AdvancedBeginner</Level>
  </Engineer>
  <Engineer>
    <Id>202670223</Id>
    <Name>Xander</Name>
    <Email>Xander@gmail.com</Email>
    <Level>Competent</Level>
  </Engineer>
  <Engineer>
    <Id>357940443</Id>
    <Name>Yasmine</Name>
    <Email>Yasmine@gmail.com</Email>
    <Level>Novice</Level>
  </Engineer>
  <Engineer>
    <Id>358034387</Id>
    <Name>Zoe</Name>
    <Email>Zoe@gmail.com</Email>
    <Level>Novice</Level>
  </Engineer>
  <Engineer>
    <Id>243671117</Id>
    <Name>Aaron</Name>
    <Email>Aaron@gmail.com</Email>
    <Level>Competent</Level>
  </Engineer>
  <Engineer>
    <Id>244701132</Id>
    <Name>Bella</Name>
    <Email>Bella@gmail.com</Email>
    <Level>AdvancedBeginner</Level>
  </Engineer>
  <Engineer>
    <Id>210352765</Id>
    <Name>Charles</Name>
    <Email>Charles@gmail.com</Email>
    <Level>Novice</Level>
  </Engineer>
  <Engineer>
    <Id>390644130</Id>
    <Name>Daisy</Name>
    <Email>Daisy@gmail.com</Email>
    <Level>Competent</Level>
  </Engineer>
  <Engineer>
    <Id>262541798</Id>
    <Name>Eli</Name>
    <Email>Eli@gmail.com</Email>
    <Level>Novice</Level>
  </Engineer>
  <Engineer>
    <Id>309939859</Id>
    <Name>Fiona</Name>
    <Email>Fiona@gmail.com</Email>
    <Level>Novice</Level>
  </Engineer>
  <Engineer>
    <Id>331783353</Id>
    <Name>George</Name>
    <Email>George@gmail.com</Email>
    <Level>AdvancedBeginner</Level>
  </Engineer>
  <Engineer>
    <Id>200427106</Id>
    <Name>Hannah</Name>
    <Email>Hannah@gmail.com</Email>
    <Level>Expert</Level>
  </Engineer>
  <Engineer>
    <Id>263991842</Id>
    <Name>Isabella</Name>
    <Email>Isabella@gmail.com</Email>
    <Level>Novice</Level>
  </Engineer>
  <Engineer>
    <Id>310453758</Id>
    <Name>John</Name>
    <Email>John@gmail.com</Email>
    <Level>Proficient</Level>
  </Engineer>
  <Engineer>
    <Id>235265045</Id>
    <Name>Katherine</Name>
    <Email>Katherine@gmail.com</Email>
    <Level>Proficient</Level>
  </Engineer>
  <Engineer>
    <Id>231314069</Id>
    <Name>Leo</Name>
    <Email>Leo@gmail.com</Email>
    <Level>Competent</Level>
  </Engineer>
  <Engineer>
    <Id>344711070</Id>
    <Name>Madison</Name>
    <Email>Madison@gmail.com</Email>
    <Level>Novice</Level>
  </Engineer>
  <Engineer>
    <Id>226311607</Id>
    <Name>Natalie</Name>
    <Email>Natalie@gmail.com</Email>
    <Level>AdvancedBeginner</Level>
  </Engineer>
  <Engineer>
    <Id>363479641</Id>
    <Name>Alice</Name>
    <Email>Alice@gmail.com</Email>
    <Level>Competent</Level>
  </Engineer>
  <Engineer>
    <Id>205536296</Id>
    <Name>Bob</Name>
    <Email>Bob@gmail.com</Email>
    <Level>AdvancedBeginner</Level>
  </Engineer>
  <Engineer>
    <Id>243978014</Id>
    <Name>Carol</Name>
    <Email>Carol@gmail.com</Email>
    <Level>Proficient</Level>
  </Engineer>
  <Engineer>
    <Id>223263988</Id>
    <Name>David</Name>
    <Email>David@gmail.com</Email>
    <Level>Competent</Level>
  </Engineer>
  <Engineer>
    <Id>396838391</Id>
    <Name>Emma</Name>
    <Email>Emma@gmail.com</Email>
    <Level>Competent</Level>
  </Engineer>
  <Engineer>
    <Id>209935059</Id>
    <Name>Frank</Name>
    <Email>Frank@gmail.com</Email>
    <Level>AdvancedBeginner</Level>
  </Engineer>
  <Engineer>
    <Id>357918113</Id>
    <Name>Grace</Name>
    <Email>Grace@gmail.com</Email>
    <Level>Competent</Level>
  </Engineer>
  <Engineer>
    <Id>255958195</Id>
    <Name>Henry</Name>
    <Email>Henry@gmail.com</Email>
    <Level>Expert</Level>
  </Engineer>
  <Engineer>
    <Id>305879041</Id>
    <Name>Irene</Name>
    <Email>Irene@gmail.com</Email>
    <Level>Competent</Level>
  </Engineer>
  <Engineer>
    <Id>271849943</Id>
    <Name>Jack</Name>
    <Email>Jack@gmail.com</Email>
    <Level>Expert</Level>
  </Engineer>
  <Engineer>
    <Id>223013819</Id>
    <Name>Karen</Name>
    <Email>Karen@gmail.com</Email>
    <Level>AdvancedBeginner</Level>
  </Engineer>
  <Engineer>
    <Id>220071038</Id>
    <Name>Liam</Name>
    <Email>Liam@gmail.com</Email>
    <Level>Novice</Level>
  </Engineer>
  <Engineer>
    <Id>317430612</Id>
    <Name>Megan</Name>
    <Email>Megan@gmail.com</Email>
    <Level>Competent</Level>
  </Engineer>
  <Engineer>
    <Id>254599508</Id>
    <Name>Noah</Name>
    <Email>Noah@gmail.com</Email>
    <Level>Expert</Level>
  </Engineer>
  <Engineer>
    <Id>248004704</Id>
    <Name>Olivia</Name>
    <Email>Olivia@gmail.com</Email>
    <Level>Expert</Level>
  </Engineer>
  <Engineer>
    <Id>335923177</Id>
    <Name>Peter</Name>
    <Email>Peter@gmail.com</Email>
    <Level>Expert</Level>
  </Engineer>
  <Engineer>
    <Id>361307851</Id>
    <Name>Quin</Name>
    <Email>Quin@gmail.com</Email>
    <Level>Expert</Level>
  </Engineer>
  <Engineer>
    <Id>275063168</Id>
    <Name>Rachel</Name>
    <Email>Rachel@gmail.com</Email>
    <Level>Expert</Level>
  </Engineer>
  <Engineer>
    <Id>223377036</Id>
    <Name>Sam</Name>
    <Email>Sam@gmail.com</Email>
    <Level>Expert</Level>
  </Engineer>
  <Engineer>
    <Id>353530478</Id>
    <Name>Taylor</Name>
    <Email>Taylor@gmail.com</Email>
    <Level>AdvancedBeginner</Level>
  </Engineer>
  <Engineer>
    <Id>231951087</Id>
    <Name>Ulysses</Name>
    <Email>Ulysses@gmail.com</Email>
    <Level>Competent</Level>
  </Engineer>
  <Engineer>
    <Id>211293290</Id>
    <Name>Victoria</Name>
    <Email>Victoria@gmail.com</Email>
    <Level>Competent</Level>
  </Engineer>
  <Engineer>
    <Id>203263434</Id>
    <Name>William</Name>
    <Email>William@gmail.com</Email>
    <Level>Novice</Level>
  </Engineer>
  <Engineer>
    <Id>228007368</Id>
    <Name>Xander</Name>
    <Email>Xander@gmail.com</Email>
    <Level>Novice</Level>
  </Engineer>
  <Engineer>
    <Id>273773865</Id>
    <Name>Yasmine</Name>
    <Email>Yasmine@gmail.com</Email>
    <Level>AdvancedBeginner</Level>
  </Engineer>
  <Engineer>
    <Id>217995091</Id>
    <Name>Zoe</Name>
    <Email>Zoe@gmail.com</Email>
    <Level>Expert</Level>
  </Engineer>
  <Engineer>
    <Id>306535678</Id>
    <Name>Aaron</Name>
    <Email>Aaron@gmail.com</Email>
    <Level>Novice</Level>
  </Engineer>
  <Engineer>
    <Id>297963592</Id>
    <Name>Bella</Name>
    <Email>Bella@gmail.com</Email>
    <Level>Novice</Level>
  </Engineer>
  <Engineer>
    <Id>292232313</Id>
    <Name>Charles</Name>
    <Email>Charles@gmail.com</Email>
    <Level>Expert</Level>
  </Engineer>
  <Engineer>
    <Id>216780689</Id>
    <Name>Daisy</Name>
    <Email>Daisy@gmail.com</Email>
    <Level>Competent</Level>
  </Engineer>
  <Engineer>
    <Id>388839342</Id>
    <Name>Eli</Name>
    <Email>Eli@gmail.com</Email>
    <Level>Proficient</Level>
  </Engineer>
  <Engineer>
    <Id>323469540</Id>
    <Name>Fiona</Name>
    <Email>Fiona@gmail.com</Email>
    <Level>Competent</Level>
  </Engineer>
  <Engineer>
    <Id>306913351</Id>
    <Name>George</Name>
    <Email>George@gmail.com</Email>
    <Level>Proficient</Level>
  </Engineer>
  <Engineer>
    <Id>244582381</Id>
    <Name>Hannah</Name>
    <Email>Hannah@gmail.com</Email>
    <Level>Expert</Level>
  </Engineer>
  <Engineer>
    <Id>370667742</Id>
    <Name>Isabella</Name>
    <Email>Isabella@gmail.com</Email>
    <Level>Expert</Level>
  </Engineer>
  <Engineer>
    <Id>305718499</Id>
    <Name>John</Name>
    <Email>John@gmail.com</Email>
    <Level>Expert</Level>
  </Engineer>
  <Engineer>
    <Id>219462335</Id>
    <Name>Katherine</Name>
    <Email>Katherine@gmail.com</Email>
    <Level>Novice</Level>
  </Engineer>
  <Engineer>
    <Id>364992673</Id>
    <Name>Leo</Name>
    <Email>Leo@gmail.com</Email>
    <Level>Proficient</Level>
  </Engineer>
  <Engineer>
    <Id>254976369</Id>
    <Name>Madison</Name>
    <Email>Madison@gmail.com</Email>
    <Level>Proficient</Level>
  </Engineer>
  <Engineer>
    <Id>372112379</Id>
    <Name>Natalie</Name>
    <Email>Natalie@gmail.com</Email>
    <Level>Novice</Level>
  </Engineer>
  <Engineer>
    <Id>291096217</Id>
    <Name>Alice</Name>
    <Email>Alice@gmail.com</Email>
    <Level>Proficient</Level>
  </Engineer>
  <Engineer>
    <Id>347912036</Id>
    <Name>Bob</Name>
    <Email>Bob@gmail.com</Email>
    <Level>Expert</Level>
  </Engineer>
  <Engineer>
    <Id>209833459</Id>
    <Name>Carol</Name>
    <Email>Carol@gmail.com</Email>
    <Level>Competent</Level>
  </Engineer>
  <Engineer>
    <Id>273001393</Id>
    <Name>David</Name>
    <Email>David@gmail.com</Email>
    <Level>Expert</Level>
  </Engineer>
  <Engineer>
    <Id>332126756</Id>
    <Name>Emma</Name>
    <Email>Emma@gmail.com</Email>
    <Level>AdvancedBeginner</Level>
  </Engineer>
  <Engineer>
    <Id>361696367</Id>
    <Name>Frank</Name>
    <Email>Frank@gmail.com</Email>
    <Level>Novice</Level>
  </Engineer>
  <Engineer>
    <Id>331013821</Id>
    <Name>Grace</Name>
    <Email>Grace@gmail.com</Email>
    <Level>Expert</Level>
  </Engineer>
  <Engineer>
    <Id>278461509</Id>
    <Name>Henry</Name>
    <Email>Henry@gmail.com</Email>
    <Level>Proficient</Level>
  </Engineer>
  <Engineer>
    <Id>202761231</Id>
    <Name>Irene</Name>
    <Email>Irene@gmail.com</Email>
    <Level>Expert</Level>
  </Engineer>
  <Engineer>
    <Id>313658000</Id>
    <Name>Jack</Name>
    <Email>Jack@gmail.com</Email>
    <Level>Proficient</Level>
  </Engineer>
  <Engineer>
    <Id>348003524</Id>
    <Name>Karen</Name>
    <Email>Karen@gmail.com</Email>
    <Level>AdvancedBeginner</Level>
  </Engineer>
  <Engineer>
    <Id>340804257</Id>
    <Name>Liam</Name>
    <Email>Liam@gmail.com</Email>
    <Level>Novice</Level>
  </Engineer>
  <Engineer>
    <Id>285447594</Id>
    <Name>Megan</Name>
    <Email>Megan@gmail.com</Email>
    <Level>Proficient</Level>
  </Engineer>
  <Engineer>
    <Id>288459300</Id>
    <Name>Noah</Name>
    <Email>Noah@gmail.com</Email>
    <Level>Proficient</Level>
  </Engineer>
  <Engineer>
    <Id>220649714</Id>
    <Name>Olivia</Name>
    <Email>Olivia@gmail.com</Email>
    <Level>Proficient</Level>
  </Engineer>
  <Engineer>
    <Id>346366034</Id>
    <Name>Peter</Name>
    <Email>Peter@gmail.com</Email>
    <Level>Proficient</Level>
  </Engineer>
  <Engineer>
    <Id>270114251</Id>
    <Name>Quin</Name>
    <Email>Quin@gmail.com</Email>
    <Level>Proficient</Level>
  </Engineer>
  <Engineer>
    <Id>304960220</Id>
    <Name>Rachel</Name>
    <Email>Rachel@gmail.com</Email>
    <Level>Proficient</Level>
  </Engineer>
  <Engineer>
    <Id>213355199</Id>
    <Name>Sam</Name>
    <Email>Sam@gmail.com</Email>
    <Level>Competent</Level>
  </Engineer>
  <Engineer>
    <Id>374269827</Id>
    <Name>Taylor</Name>
    <Email>Taylor@gmail.com</Email>
    <Level>AdvancedBeginner</Level>
  </Engineer>
  <Engineer>
    <Id>291104279</Id>
    <Name>Ulysses</Name>
    <Email>Ulysses@gmail.com</Email>
    <Level>Novice</Level>
  </Engineer>
  <Engineer>
    <Id>325223663</Id>
    <Name>Victoria</Name>
    <Email>Victoria@gmail.com</Email>
    <Level>Competent</Level>
  </Engineer>
  <Engineer>
    <Id>367452316</Id>
    <Name>William</Name>
    <Email>William@gmail.com</Email>
    <Level>Competent</Level>
  </Engineer>
  <Engineer>
    <Id>297563918</Id>
    <Name>Xander</Name>
    <Email>Xander@gmail.com</Email>
    <Level>AdvancedBeginner</Level>
  </Engineer>
  <Engineer>
    <Id>287547605</Id>
    <Name>Yasmine</Name>
    <Email>Yasmine@gmail.com</Email>
    <Level>Expert</Level>
  </Engineer>
  <Engineer>
    <Id>209046018</Id>
    <Name>Zoe</Name>
    <Email>Zoe@gmail.com</Email>
    <Level>AdvancedBeginner</Level>
  </Engineer>
  <Engineer>
    <Id>327066758</Id>
    <Name>Aaron</Name>
    <Email>Aaron@gmail.com</Email>
    <Level>Novice</Level>
  </Engineer>
  <Engineer>
    <Id>364015773</Id>
    <Name>Bella</Name>
    <Email>Bella@gmail.com</Email>
    <Level>Expert</Level>
  </Engineer>
  <Engineer>
    <Id>298534839</Id>
    <Name>Charles</Name>
    <Email>Charles@gmail.com</Email>
    <Level>Proficient</Level>
  </Engineer>
  <Engineer>
    <Id>200404060</Id>
    <Name>Daisy</Name>
    <Email>Daisy@gmail.com</Email>
    <Level>AdvancedBeginner</Level>
  </Engineer>
  <Engineer>
    <Id>202440659</Id>
    <Name>Eli</Name>
    <Email>Eli@gmail.com</Email>
    <Level>Novice</Level>
  </Engineer>
  <Engineer>
    <Id>281951004</Id>
    <Name>Fiona</Name>
    <Email>Fiona@gmail.com</Email>
    <Level>Proficient</Level>
  </Engineer>
  <Engineer>
    <Id>392750364</Id>
    <Name>George</Name>
    <Email>George@gmail.com</Email>
    <Level>Competent</Level>
  </Engineer>
  <Engineer>
    <Id>354422771</Id>
    <Name>Hannah</Name>
    <Email>Hannah@gmail.com</Email>
    <Level>Competent</Level>
  </Engineer>
  <Engineer>
    <Id>294472443</Id>
    <Name>Isabella</Name>
    <Email>Isabella@gmail.com</Email>
    <Level>Competent</Level>
  </Engineer>
  <Engineer>
    <Id>236446233</Id>
    <Name>John</Name>
    <Email>John@gmail.com</Email>
    <Level>Proficient</Level>
  </Engineer>
  <Engineer>
    <Id>336340930</Id>
    <Name>Katherine</Name>
    <Email>Katherine@gmail.com</Email>
    <Level>AdvancedBeginner</Level>
  </Engineer>
  <Engineer>
    <Id>275751653</Id>
    <Name>Leo</Name>
    <Email>Leo@gmail.com</Email>
    <Level>Proficient</Level>
  </Engineer>
  <Engineer>
    <Id>350837215</Id>
    <Name>Madison</Name>
    <Email>Madison@gmail.com</Email>
    <Level>Competent</Level>
  </Engineer>
  <Engineer>
    <Id>260127753</Id>
    <Name>Natalie</Name>
    <Email>Natalie@gmail.com</Email>
    <Level>AdvancedBeginner</Level>
  </Engineer>
  <Engineer>
    <Id>258177417</Id>
    <Name>Alice</Name>
    <Email>Alice@gmail.com</Email>
    <Level>Expert</Level>
  </Engineer>
  <Engineer>
    <Id>297598908</Id>
    <Name>Bob</Name>
    <Email>Bob@gmail.com</Email>
    <Level>Competent</Level>
  </Engineer>
  <Engineer>
    <Id>253267736</Id>
    <Name>Carol</Name>
    <Email>Carol@gmail.com</Email>
    <Level>Novice</Level>
  </Engineer>
  <Engineer>
    <Id>294808788</Id>
    <Name>David</Name>
    <Email>David@gmail.com</Email>
    <Level>AdvancedBeginner</Level>
  </Engineer>
  <Engineer>
    <Id>261947674</Id>
    <Name>Emma</Name>
    <Email>Emma@gmail.com</Email>
    <Level>Proficient</Level>
  </Engineer>
  <Engineer>
    <Id>282591627</Id>
    <Name>Frank</Name>
    <Email>Frank@gmail.com</Email>
    <Level>Proficient</Level>
  </Engineer>
  <Engineer>
    <Id>332842096</Id>
    <Name>Grace</Name>
    <Email>Grace@gmail.com</Email>
    <Level>Novice</Level>
  </Engineer>
  <Engineer>
    <Id>252664604</Id>
    <Name>Henry</Name>
    <Email>Henry@gmail.com</Email>
    <Level>Competent</Level>
  </Engineer>
  <Engineer>
    <Id>244817219</Id>
    <Name>Irene</Name>
    <Email>Irene@gmail.com</Email>
    <Level>Proficient</Level>
  </Engineer>
  <Engineer>
    <Id>259435023</Id>
    <Name>Jack</Name>
    <Email>Jack@gmail.com</Email>
    <Level>Competent</Level>
  </Engineer>
  <Engineer>
    <Id>207487933</Id>
    <Name>Karen</Name>
    <Email>Karen@gmail.com</Email>
    <Level>Proficient</Level>
  </Engineer>
  <Engineer>
    <Id>375049154</Id>
    <Name>Liam</Name>
    <Email>Liam@gmail.com</Email>
    <Level>Competent</Level>
  </Engineer>
  <Engineer>
    <Id>342136957</Id>
    <Name>Megan</Name>
    <Email>Megan@gmail.com</Email>
    <Level>Proficient</Level>
  </Engineer>
  <Engineer>
    <Id>204402470</Id>
    <Name>Noah</Name>
    <Email>Noah@gmail.com</Email>
    <Level>Competent</Level>
  </Engineer>
  <Engineer>
    <Id>224263025</Id>
    <Name>Olivia</Name>
    <Email>Olivia@gmail.com</Email>
    <Level>Expert</Level>
  </Engineer>
  <Engineer>
    <Id>247790752</Id>
    <Name>Peter</Name>
    <Email>Peter@gmail.com</Email>
    <Level>Expert</Level>
  </Engineer>
  <Engineer>
    <Id>279387966</Id>
    <Name>Quin</Name>
    <Email>Quin@gmail.com</Email>
    <Level>Competent</Level>
  </Engineer>
  <Engineer>
    <Id>266777359</Id>
    <Name>Rachel</Name>
    <Email>Rachel@gmail.com</Email>
    <Level>Novice</Level>
  </Engineer>
  <Engineer>
    <Id>328396908</Id>
    <Name>Sam</Name>
    <Email>Sam@gmail.com</Email>
    <Level>Competent</Level>
  </Engineer>
  <Engineer>
    <Id>389762480</Id>
    <Name>Taylor</Name>
    <Email>Taylor@gmail.com</Email>
    <Level>Expert</Level>
  </Engineer>
  <Engineer>
    <Id>244521214</Id>
    <Name>Ulysses</Name>
    <Email>Ulysses@gmail.com</Email>
    <Level>Proficient</Level>
  </Engineer>
  <Engineer>
    <Id>216989473</Id>
    <Name>Victoria</Name>
    <Email>Victoria@gmail.com</Email>
    <Level>Expert</Level>
  </Engineer>
  <Engineer>
    <Id>271332154</Id>
    <Name>William</Name>
    <Email>William@gmail.com</Email>
    <Level>Novice</Level>
  </Engineer>
  <Engineer>
    <Id>399196533</Id>
    <Name>Xander</Name>
    <Email>Xander@gmail.com</Email>
    <Level>Expert</Level>
  </Engineer>
  <Engineer>
    <Id>305023830</Id>
    <Name>Yasmine</Name>
    <Email>Yasmine@gmail.com</Email>
    <Level>Competent</Level>
  </Engineer>
  <Engineer>
    <Id>278677468</Id>
    <Name>Zoe</Name>
    <Email>Zoe@gmail.com</Email>
    <Level>Novice</Level>
  </Engineer>
  <Engineer>
    <Id>299153981</Id>
    <Name>Aaron</Name>
    <Email>Aaron@gmail.com</Email>
    <Level>Proficient</Level>
  </Engineer>
  <Engineer>
    <Id>372190323</Id>
    <Name>Bella</Name>
    <Email>Bella@gmail.com</Email>
    <Level>Expert</Level>
  </Engineer>
  <Engineer>
    <Id>290919484</Id>
    <Name>Charles</Name>
    <Email>Charles@gmail.com</Email>
    <Level>Novice</Level>
  </Engineer>
  <Engineer>
    <Id>392905236</Id>
    <Name>Daisy</Name>
    <Email>Daisy@gmail.com</Email>
    <Level>Competent</Level>
  </Engineer>
  <Engineer>
    <Id>224533506</Id>
    <Name>Eli</Name>
    <Email>Eli@gmail.com</Email>
    <Level>Expert</Level>
  </Engineer>
  <Engineer>
    <Id>296961837</Id>
    <Name>Fiona</Name>
    <Email>Fiona@gmail.com</Email>
    <Level>Novice</Level>
  </Engineer>
  <Engineer>
    <Id>225443108</Id>
    <Name>George</Name>
    <Email>George@gmail.com</Email>
    <Level>Competent</Level>
  </Engineer>
  <Engineer>
    <Id>210875265</Id>
    <Name>Hannah</Name>
    <Email>Hannah@gmail.com</Email>
    <Level>Proficient</Level>
  </Engineer>
  <Engineer>
    <Id>212020313</Id>
    <Name>Isabella</Name>
    <Email>Isabella@gmail.com</Email>
    <Level>Expert</Level>
  </Engineer>
  <Engineer>
    <Id>304848807</Id>
    <Name>John</Name>
    <Email>John@gmail.com</Email>
    <Level>Competent</Level>
  </Engineer>
  <Engineer>
    <Id>234213474</Id>
    <Name>Katherine</Name>
    <Email>Katherine@gmail.com</Email>
    <Level>Expert</Level>
  </Engineer>
  <Engineer>
    <Id>309347389</Id>
    <Name>Leo</Name>
    <Email>Leo@gmail.com</Email>
    <Level>Novice</Level>
  </Engineer>
  <Engineer>
    <Id>302687185</Id>
    <Name>Madison</Name>
    <Email>Madison@gmail.com</Email>
    <Level>AdvancedBeginner</Level>
  </Engineer>
  <Engineer>
    <Id>223235882</Id>
    <Name>Natalie</Name>
    <Email>Natalie@gmail.com</Email>
    <Level>Competent</Level>
  </Engineer>
  <Engineer>
    <Id>305477290</Id>
    <Name>Alice</Name>
    <Email>Alice@gmail.com</Email>
    <Level>Proficient</Level>
  </Engineer>
  <Engineer>
    <Id>373381833</Id>
    <Name>Bob</Name>
    <Email>Bob@gmail.com</Email>
    <Level>AdvancedBeginner</Level>
  </Engineer>
  <Engineer>
    <Id>334805732</Id>
    <Name>Carol</Name>
    <Email>Carol@gmail.com</Email>
    <Level>Novice</Level>
  </Engineer>
  <Engineer>
    <Id>233963562</Id>
    <Name>David</Name>
    <Email>David@gmail.com</Email>
    <Level>Novice</Level>
  </Engineer>
  <Engineer>
    <Id>219238869</Id>
    <Name>Emma</Name>
    <Email>Emma@gmail.com</Email>
    <Level>Novice</Level>
  </Engineer>
  <Engineer>
    <Id>203612468</Id>
    <Name>Frank</Name>
    <Email>Frank@gmail.com</Email>
    <Level>AdvancedBeginner</Level>
  </Engineer>
  <Engineer>
    <Id>341863125</Id>
    <Name>Grace</Name>
    <Email>Grace@gmail.com</Email>
    <Level>AdvancedBeginner</Level>
  </Engineer>
  <Engineer>
    <Id>278615737</Id>
    <Name>Henry</Name>
    <Email>Henry@gmail.com</Email>
    <Level>Proficient</Level>
  </Engineer>
  <Engineer>
    <Id>381591366</Id>
    <Name>Irene</Name>
    <Email>Irene@gmail.com</Email>
    <Level>AdvancedBeginner</Level>
  </Engineer>
  <Engineer>
    <Id>330661969</Id>
    <Name>Jack</Name>
    <Email>Jack@gmail.com</Email>
    <Level>Novice</Level>
  </Engineer>
  <Engineer>
    <Id>229492783</Id>
    <Name>Karen</Name>
    <Email>Karen@gmail.com</Email>
    <Level>Competent</Level>
  </Engineer>
  <Engineer>
    <Id>252308570</Id>
    <Name>Liam</Name>
    <Email>Liam@gmail.com</Email>
    <Level>Novice</Level>
  </Engineer>
  <Engineer>
    <Id>224286904</Id>
    <Name>Megan</Name>
    <Email>Megan@gmail.com</Email>
    <Level>AdvancedBeginner</Level>
  </Engineer>
  <Engineer>
    <Id>263422229</Id>
    <Name>Noah</Name>
    <Email>Noah@gmail.com</Email>
    <Level>Proficient</Level>
  </Engineer>
  <Engineer>
    <Id>359020445</Id>
    <Name>Olivia</Name>
    <Email>Olivia@gmail.com</Email>
    <Level>Competent</Level>
  </Engineer>
  <Engineer>
    <Id>256367989</Id>
    <Name>Peter</Name>
    <Email>Peter@gmail.com</Email>
    <Level>Proficient</Level>
  </Engineer>
  <Engineer>
    <Id>227466599</Id>
    <Name>Quin</Name>
    <Email>Quin@gmail.com</Email>
    <Level>Expert</Level>
  </Engineer>
  <Engineer>
    <Id>220436160</Id>
    <Name>Rachel</Name>
    <Email>Rachel@gmail.com</Email>
    <Level>Proficient</Level>
  </Engineer>
  <Engineer>
    <Id>375007281</Id>
    <Name>Sam</Name>
    <Email>Sam@gmail.com</Email>
    <Level>Novice</Level>
  </Engineer>
  <Engineer>
    <Id>354937604</Id>
    <Name>Taylor</Name>
    <Email>Taylor@gmail.com</Email>
    <Level>Proficient</Level>
  </Engineer>
  <Engineer>
    <Id>286807081</Id>
    <Name>Ulysses</Name>
    <Email>Ulysses@gmail.com</Email>
    <Level>Proficient</Level>
  </Engineer>
  <Engineer>
    <Id>292082956</Id>
    <Name>Victoria</Name>
    <Email>Victoria@gmail.com</Email>
    <Level>AdvancedBeginner</Level>
  </Engineer>
  <Engineer>
    <Id>201017921</Id>
    <Name>William</Name>
    <Email>William@gmail.com</Email>
    <Level>Proficient</Level>
  </Engineer>
  <Engineer>
    <Id>272326057</Id>
    <Name>Xander</Name>
    <Email>Xander@gmail.com</Email>
    <Level>Competent</Level>
  </Engineer>
  <Engineer>
    <Id>318744732</Id>
    <Name>Yasmine</Name>
    <Email>Yasmine@gmail.com</Email>
    <Level>AdvancedBeginner</Level>
  </Engineer>
  <Engineer>
    <Id>208183620</Id>
    <Name>Zoe</Name>
    <Email>Zoe@gmail.com</Email>
    <Level>AdvancedBeginner</Level>
  </Engineer>
  <Engineer>
    <Id>265604077</Id>
    <Name>Aaron</Name>
    <Email>Aaron@gmail.com</Email>
    <Level>Competent</Level>
  </Engineer>
  <Engineer>
    <Id>210265859</Id>
    <Name>Bella</Name>
    <Email>Bella@gmail.com</Email>
    <Level>Competent</Level>
  </Engineer>
  <Engineer>
    <Id>204339397</Id>
    <Name>Charles</Name>
    <Email>Charles@gmail.com</Email>
    <Level>Expert</Level>
  </Engineer>
  <Engineer>
    <Id>386238545</Id>
    <Name>Daisy</Name>
    <Email>Daisy@gmail.com</Email>
    <Level>AdvancedBeginner</Level>
  </Engineer>
  <Engineer>
    <Id>366199158</Id>
    <Name>Eli</Name>
    <Email>Eli@gmail.com</Email>
    <Level>Competent</Level>
  </Engineer>
  <Engineer>
    <Id>255672466</Id>
    <Name>Fiona</Name>
    <Email>Fiona@gmail.com</Email>
    <Level>Proficient</Level>
  </Engineer>
  <Engineer>
    <Id>366143065</Id>
    <Name>George</Name>
    <Email>George@gmail.com</Email>
    <Level>Expert</Level>
  </Engineer>
  <Engineer>
    <Id>318796572</Id>
    <Name>Hannah</Name>
    <Email>Hannah@gmail.com</Email>
    <Level>AdvancedBeginner</Level>
  </Engineer>
  <Engineer>
    <Id>353287942</Id>
    <Name>Isabella</Name>
    <Email>Isabella@gmail.com</Email>
    <Level>Expert</Level>
  </Engineer>
  <Engineer>
    <Id>284239916</Id>
    <Name>John</Name>
    <Email>John@gmail.com</Email>
    <Level>AdvancedBeginner</Level>
  </Engineer>
  <Engineer>
    <Id>247185433</Id>
    <Name>Katherine</Name>
    <Email>Katherine@gmail.com</Email>
    <Level>Expert</Level>
  </Engineer>
  <Engineer>
    <Id>235923185</Id>
    <Name>Leo</Name>
    <Email>Leo@gmail.com</Email>
    <Level>Competent</Level>
  </Engineer>
  <Engineer>
    <Id>221923415</Id>
    <Name>Madison</Name>
    <Email>Madison@gmail.com</Email>
    <Level>Novice</Level>
  </Engineer>
  <Engineer>
    <Id>372743402</Id>
    <Name>Natalie</Name>
    <Email>Natalie@gmail.com</Email>
    <Level>Competent</Level>
  </Engineer>
  <Engineer>
    <Id>383435924</Id>
    <Name>Alice</Name>
    <Email>Alice@gmail.com</Email>
    <Level>Proficient</Level>
  </Engineer>
  <Engineer>
    <Id>388284096</Id>
    <Name>Bob</Name>
    <Email>Bob@gmail.com</Email>
    <Level>Expert</Level>
  </Engineer>
  <Engineer>
    <Id>281068060</Id>
    <Name>Carol</Name>
    <Email>Carol@gmail.com</Email>
    <Level>Competent</Level>
  </Engineer>
  <Engineer>
    <Id>305114345</Id>
    <Name>David</Name>
    <Email>David@gmail.com</Email>
    <Level>AdvancedBeginner</Level>
  </Engineer>
  <Engineer>
    <Id>291947565</Id>
    <Name>Emma</Name>
    <Email>Emma@gmail.com</Email>
    <Level>Proficient</Level>
  </Engineer>
  <Engineer>
    <Id>216503080</Id>
    <Name>Frank</Name>
    <Email>Frank@gmail.com</Email>
    <Level>Proficient</Level>
  </Engineer>
  <Engineer>
    <Id>321259276</Id>
    <Name>Grace</Name>
    <Email>Grace@gmail.com</Email>
    <Level>Proficient</Level>
  </Engineer>
  <Engineer>
    <Id>314784490</Id>
    <Name>Henry</Name>
    <Email>Henry@gmail.com</Email>
    <Level>Proficient</Level>
  </Engineer>
  <Engineer>
    <Id>292045287</Id>
    <Name>Irene</Name>
    <Email>Irene@gmail.com</Email>
    <Level>Expert</Level>
  </Engineer>
  <Engineer>
    <Id>305428106</Id>
    <Name>Jack</Name>
    <Email>Jack@gmail.com</Email>
    <Level>Proficient</Level>
  </Engineer>
  <Engineer>
    <Id>237459186</Id>
    <Name>Karen</Name>
    <Email>Karen@gmail.com</Email>
    <Level>Expert</Level>
  </Engineer>
  <Engineer>
    <Id>320519459</Id>
    <Name>Liam</Name>
    <Email>Liam@gmail.com</Email>
    <Level>Competent</Level>
  </Engineer>
  <Engineer>
    <Id>256770571</Id>
    <Name>Megan</Name>
    <Email>Megan@gmail.com</Email>
    <Level>Novice</Level>
  </Engineer>
  <Engineer>
    <Id>271437517</Id>
    <Name>Noah</Name>
    <Email>Noah@gmail.com</Email>
    <Level>Competent</Level>
  </Engineer>
  <Engineer>
    <Id>209734147</Id>
    <Name>Olivia</Name>
    <Email>Olivia@gmail.com</Email>
    <Level>Novice</Level>
  </Engineer>
  <Engineer>
    <Id>237319455</Id>
    <Name>Peter</Name>
    <Email>Peter@gmail.com</Email>
    <Level>Expert</Level>
  </Engineer>
  <Engineer>
    <Id>310955794</Id>
    <Name>Quin</Name>
    <Email>Quin@gmail.com</Email>
    <Level>AdvancedBeginner</Level>
  </Engineer>
  <Engineer>
    <Id>270393612</Id>
    <Name>Rachel</Name>
    <Email>Rachel@gmail.com</Email>
    <Level>Expert</Level>
  </Engineer>
  <Engineer>
    <Id>321001046</Id>
    <Name>Sam</Name>
    <Email>Sam@gmail.com</Email>
    <Level>Competent</Level>
  </Engineer>
  <Engineer>
    <Id>213953294</Id>
    <Name>Taylor</Name>
    <Email>Taylor@gmail.com</Email>
    <Level>Competent</Level>
  </Engineer>
  <Engineer>
    <Id>266420794</Id>
    <Name>Ulysses</Name>
    <Email>Ulysses@gmail.com</Email>
    <Level>Novice</Level>
  </Engineer>
  <Engineer>
    <Id>272753898</Id>
    <Name>Victoria</Name>
    <Email>Victoria@gmail.com</Email>
    <Level>Novice</Level>
  </Engineer>
  <Engineer>
    <Id>257656786</Id>
    <Name>William</Name>
    <Email>William@gmail.com</Email>
    <Level>Competent</Level>
  </Engineer>
  <Engineer>
    <Id>213224792</Id>
    <Name>Xander</Name>
    <Email>Xander@gmail.com</Email>
    <Level>Proficient</Level>
  </Engineer>
  <Engineer>
    <Id>233065768</Id>
    <Name>Yasmine</Name>
    <Email>Yasmine@gmail.com</Email>
    <Level>Novice</Level>
  </Engineer>
  <Engineer>
    <Id>288801946</Id>
    <Name>Zoe</Name>
    <Email>Zoe@gmail.com</Email>
    <Level>Proficient</Level>
  </Engineer>
  <Engineer>
    <Id>266327116</Id>
    <Name>Aaron</Name>
    <Email>Aaron@gmail.com</Email>
    <Level>AdvancedBeginner</Level>
  </Engineer>
  <Engineer>
    <Id>275859152</Id>
    <Name>Bella</Name>
    <Email>Bella@gmail.com</Email>
    <Level>AdvancedBeginner</Level>
  </Engineer>
  <Engineer>
    <Id>395482800</Id>
    <Name>Charles</Name>
    <Email>Charles@gmail.com</Email>
    <Level>Competent</Level>
  </Engineer>
  <Engineer>
    <Id>298278477</Id>
    <Name>Daisy</Name>
    <Email>Daisy@gmail.com</Email>
    <Level>Competent</Level>
  </Engineer>
  <Engineer>
    <Id>352365928</Id>
    <Name>Eli</Name>
    <Email>Eli@gmail.com</Email>
    <Level>Expert</Level>
  </Engineer>
  <Engineer>
    <Id>253695523</Id>
    <Name>Fiona</Name>
    <Email>Fiona@gmail.com</Email>
    <Level>Proficient</Level>
  </Engineer>
  <Engineer>
    <Id>221554023</Id>
    <Name>George</Name>
    <Email>George@gmail.com</Email>
    <Level>AdvancedBeginner</Level>
  </Engineer>
  <Engineer>
    <Id>284090232</Id>
    <Name>Hannah</Name>
    <Email>Hannah@gmail.com</Email>
    <Level>Expert</Level>
  </Engineer>
  <Engineer>
    <Id>224868242</Id>
    <Name>Isabella</Name>
    <Email>Isabella@gmail.com</Email>
    <Level>Competent</Level>
  </Engineer>
  <Engineer>
    <Id>282437781</Id>
    <Name>John</Name>
    <Email>John@gmail.com</Email>
    <Level>Competent</Level>
  </Engineer>
  <Engineer>
    <Id>212288609</Id>
    <Name>Katherine</Name>
    <Email>Katherine@gmail.com</Email>
    <Level>Proficient</Level>
  </Engineer>
  <Engineer>
    <Id>383520997</Id>
    <Name>Leo</Name>
    <Email>Leo@gmail.com</Email>
    <Level>AdvancedBeginner</Level>
  </Engineer>
  <Engineer>
    <Id>206204626</Id>
    <Name>Madison</Name>
    <Email>Madison@gmail.com</Email>
    <Level>Competent</Level>
  </Engineer>
  <Engineer>
    <Id>389736474</Id>
    <Name>Natalie</Name>
    <Email>Natalie@gmail.com</Email>
    <Level>Competent</Level>
  </Engineer>
</ArrayOfEngineer>